libcppyy.cpython-36m-x86_64-linux-gnu.so
CPyCppyy-1.3.6.dist-info/LICENSE.txt
CPyCppyy-1.3.6.dist-info/METADATA
CPyCppyy-1.3.6.dist-info/RECORD
CPyCppyy-1.3.6.dist-info/WHEEL
CPyCppyy-1.3.6.dist-info/top_level.txt
