Metadata-Version: 2.1
Name: CPyCppyy
Version: 1.3.6
Summary: Cling-based Python-C++ bindings for CPython
Home-page: http://cppyy.readthedocs.io/
Author: Wim Lavrijsen
Author-email: WLavrijsen@lbl.gov
License: LBNL BSD
Keywords: C++ bindings data science
Platform: UNKNOWN
Classifier: Development Status :: 5 - Production/Stable
Classifier: Intended Audience :: Developers
Classifier: Topic :: Software Development
Classifier: Topic :: Software Development :: Interpreters
Classifier: License :: OSI Approved :: BSD License
Classifier: Programming Language :: Python :: 2
Classifier: Programming Language :: Python :: 2.7
Classifier: Programming Language :: Python :: 3
Classifier: Programming Language :: Python :: 3.6
Classifier: Programming Language :: Python :: 3.7
Classifier: Programming Language :: C
Classifier: Programming Language :: C++
Classifier: Natural Language :: English
Requires-Dist: cppyy-backend (>=1.3)
